AUTHORS
LICENSE
MANIFEST.in
README.rst
requirements-dev.txt
requirements.txt
setup.cfg
setup.py
versify/__init__.py
versify.egg-info/PKG-INFO
versify.egg-info/SOURCES.txt
versify.egg-info/dependency_links.txt
versify.egg-info/requires.txt
versify.egg-info/top_level.txt
versify/model/Book.py
versify/model/Chapter.py
versify/model/Testament.py
versify/model/Verse.py
versify/model/Version.py
versify/model/__init__.py
versify/util/Dbt.py
versify/util/__init__.py