Metadata-Version: 1.1
Name: versify
Version: 0.1.3
Summary: Client for DBT API Platform
Home-page: https://github.com/willinprogress/python-versify
Author: Willy K.
Author-email: willy.konguem@gmail.com
License: UNKNOWN
Platform: UNKNOWN
Classifier: Programming Language :: Python
Classifier: Development Status :: 1 - Planning
Classifier: Operating System :: OS Independent
Classifier: Programming Language :: Python :: 2
Classifier: Programming Language :: Python :: 2.7
Classifier: Programming Language :: Python :: 3
